README.md
setup.cfg
setup.py
approxeng.input.egg-info/PKG-INFO
approxeng.input.egg-info/SOURCES.txt
approxeng.input.egg-info/dependency_links.txt
approxeng.input.egg-info/entry_points.txt
approxeng.input.egg-info/not-zip-safe
approxeng.input.egg-info/requires.txt
approxeng.input.egg-info/top_level.txt
approxeng/input/__init__.py
approxeng/input/controllers.py
approxeng/input/dualshock3.py
approxeng/input/dualshock4.py
approxeng/input/pihut.py
approxeng/input/profiling.py
approxeng/input/selectbinder.py
approxeng/input/sf30pro.py
approxeng/input/spacemousepro.py
approxeng/input/steamcontroller.py
approxeng/input/switch.py
approxeng/input/sys.py
approxeng/input/wiimote.py
approxeng/input/gui/console.py
approxeng/input/gui/controllerclasses.py
approxeng/input/gui/profiler.py
approxeng/input/yaml_controllers/__init__.py
approxeng/input/yaml_controllers/google_llc_stadia_controller_rev_a_v6353_p37888.yaml
approxeng/input/yaml_controllers/microsoft_xbox_one_s_pad_v1118_p746.yaml
approxeng/input/yaml_controllers/nintendo_wii_remote_pro_controller_v1406_p816.yaml
approxeng/input/yaml_controllers/performance_designed_products_rock_candy_wireless_gamepad_for_ps3_v3695_p296.yaml
approxeng/input/yaml_controllers/xbox_wireless_controller_v1118_p765.yaml