Metadata-Version: 2.1
Name: approxeng.input
Version: 2.6.4
Summary: Python game controller support using evDev for Raspberry Pi and other Linux systems
Home-page: https://github.com/ApproxEng/approxeng.input/
Author: Tom Oinn
Author-email: tomoinn@gmail.com
License: ASL2.0
Classifier: Programming Language :: Python :: 3.5
Requires-Dist: evdev==1.6.1
Requires-Dist: pyyaml==6.0.1
Requires-Dist: importlib-resources; python_version < "3.7"
